[
        {
            "ParameterKey": "NetworkVPCID", 
            "ParameterValue": "vpc-06f39d630ab640a15"
        },
        {
            "ParameterKey": "NetworkAddressRange", 
            "ParameterValue": "10.30.20"
        },
        {
            "ParameterKey": "NetworkExternalAddressRanges", 
            "ParameterValue": "10.29.20.0/24,10.31.20.0/24,10.32.20.0/24"
        },
        {
            "ParameterKey": "NetworkInternalHostAddressRanges",
            "ParameterValue": "10.30.10.0/24"
        },
        {
            "ParameterKey": "VNFServiceChain", 
            "ParameterValue": "WAN<->Cisco SDWAN<->Fortinet<->Hosts"
        },
        {
            "ParameterKey": "NetworkPrimaryAZ", 
            "ParameterValue": "us-east-2a"
        },
        {
            "ParameterKey": "VNFCiscoSDWANUserData", 
            "ParameterValue":  "#cloud-config\nvinitparam:\n- otp : 10358fba16f7babffad9e16c32ca1bd5\n- vbond : vbond-259910.viptela.net\n- uuid : d30830d9-8f05-45d6-84e7-452e530af4d4\n- org : BT WNBA - 20446"
        },
        {
            "ParameterKey": "MiscTimeStampCreate", 
            "ParameterValue": "Nov132018"
        },
        {
            "ParameterKey": "MiscTimeStampUpdate", 
            "ParameterValue": "Nov132018"
        }
]
